{"file":"careers-CsoeUTw7.js","mappings":";;;;;;;;;;;;;;;;;;;AA6EA,eAAW;AAAA,MACT,OAAO;AAAA,MACP,aAAa;AAAA,IAAA,CACd;AAED,UAAM,QAAQ;AAAA,MACZ,EAAE,OAAO,MAAM,OAAO,gBAAgB,aAAa,gEAAA;AAAA,MACnD,EAAE,OAAO,MAAM,OAAO,mBAAmB,aAAa,8EAAA;AAAA,MACtD,EAAE,OAAO,MAAM,OAAO,UAAU,aAAa,0DAAA;AAAA,MAC7C,EAAE,OAAO,MAAM,OAAO,mBAAmB,aAAa,mEAAA;AAAA,MACtD,EAAE,OAAO,OAAO,OAAO,iBAAiB,aAAa,4DAAA;AAAA,MACrD,EAAE,OAAO,MAAM,OAAO,eAAe,aAAa,kFAAA;AAAA,IAAkF;AAGtI,UAAM,YAAY;AAAA,MAChB,EAAE,OAAO,2BAA2B,YAAY,eAAe,UAAU,mBAAmB,MAAM,YAAA;AAAA,MAClG,EAAE,OAAO,8BAA8B,YAAY,WAAW,UAAU,mBAAmB,MAAM,YAAA;AAAA,MACjG,EAAE,OAAO,4BAA4B,YAAY,eAAe,UAAU,mBAAmB,MAAM,YAAA;AAAA,MACnG,EAAE,OAAO,sBAAsB,YAAY,sBAAsB,UAAU,UAAU,MAAM,YAAA;AAAA,MAC3F,EAAE,OAAO,kBAAkB,YAAY,SAAS,UAAU,UAAU,MAAM,YAAA;AAAA,MAC1E,EAAE,OAAO,sBAAsB,YAAY,eAAe,UAAU,mBAAmB,MAAM,YAAA;AAAA,IAAY;;;;;;;;;;QA5FnG,KAAI;AAAA,QACJ,OAAM;AAAA,QACN,aAAY;AAAA,QACZ,gBAAa;AAAA,QACb,eAAY;AAAA,QACX,MAAM;AAAA,MAAA;;AAWiBA,oBAAA,QAAR,SAAI;6FACgBC,eAAA,KAAK,KAAK,mDACIA,eAAA,KAAK,KAAK,0DACFA,eAAA,KAAK,WAAW;;;AAerDD,oBAAA,YAAR,SAAI;8QAMgCC,eAAA,KAAK,KAAK,kGAC2CA,eAAA,KAAK,UAAU,kFAGlGA,eAAA,KAAK,QAAQ,+BAEbA,eAAA,KAAK,IAAI;;;;QAgBd,IAAG;AAAA,QAAW,OAAM;AAAA,MAAA;yBAA9B,CAAsE,GAAAC,QAAAC,UAAA,aAAA;;;;;8BAA1B,iBAAe;AAAA,YAAA;AAAA;;;;;;;;;;;;;;;;","names":["_ssrRenderList","_ssrInterpolate","_push","_parent"],"sources":["../../../../pages/company/careers.vue"],"sourcesContent":["<template>\n  <div>\n    <AppHeader />\n    <main>\n      <PageHero\n        tag=\"Careers\"\n        title=\"Build the future of open finance with us\"\n        description=\"We're a team of curious, ambitious people who love building great technology. Come join us.\"\n        parent-label=\"Company\"\n        parent-href=\"/company\"\n        :dark=\"true\"\n      />\n\n      <!-- Why work here -->\n      <section class=\"py-20 bg-white\">\n        <div class=\"max-w-7xl mx-auto px-4 sm:px-6 lg:px-8\">\n          <div class=\"text-center mb-14\">\n            <p class=\"section-label\">Life at Altisry</p>\n            <h2 class=\"section-title mb-5\">Why people love working here</h2>\n          </div>\n          <div class=\"grid grid-cols-1 md:grid-cols-2 lg:grid-cols-3 gap-6\">\n            <div v-for=\"perk in perks\" :key=\"perk.title\" class=\"card hover:shadow-md transition-all\">\n              <div class=\"text-3xl mb-3\">{{ perk.emoji }}</div>\n              <h3 class=\"font-bold text-navy-900 mb-2\">{{ perk.title }}</h3>\n              <p class=\"text-sm text-gray-600 leading-relaxed\">{{ perk.description }}</p>\n            </div>\n          </div>\n        </div>\n      </section>\n\n      <!-- Open roles -->\n      <section class=\"py-20 bg-brand-50\">\n        <div class=\"max-w-4xl mx-auto px-4 sm:px-6 lg:px-8\">\n          <div class=\"text-center mb-12\">\n            <p class=\"section-label\">Open roles</p>\n            <h2 class=\"section-title mb-5\">We're hiring</h2>\n          </div>\n          <div class=\"space-y-4\">\n            <div\n              v-for=\"role in openRoles\"\n              :key=\"role.title\"\n              class=\"bg-white rounded-2xl p-6 border border-gray-100 hover:border-brand-400 hover:shadow-md transition-all cursor-pointer flex items-center justify-between group\"\n            >\n              <div>\n                <div class=\"flex items-center gap-3 mb-1\">\n                  <h3 class=\"font-bold text-navy-900\">{{ role.title }}</h3>\n                  <span class=\"text-xs bg-brand-100 text-brand-600 font-semibold px-2.5 py-1 rounded-full\">{{ role.department }}</span>\n                </div>\n                <div class=\"flex items-center gap-4 text-sm text-gray-500\">\n                  <span>{{ role.location }}</span>\n                  <span>·</span>\n                  <span>{{ role.type }}</span>\n                </div>\n              </div>\n              <svg\n                class=\"w-5 h-5 text-gray-400 group-hover:text-brand-600 group-hover:translate-x-1 transition-all\"\n                fill=\"none\"\n                stroke=\"currentColor\"\n                viewBox=\"0 0 24 24\"\n              >\n                <path stroke-linecap=\"round\" stroke-linejoin=\"round\" stroke-width=\"2\" d=\"M9 5l7 7-7 7\" />\n              </svg>\n            </div>\n          </div>\n\n          <div class=\"text-center mt-10\">\n            <p class=\"text-gray-600 mb-4\">Don't see a role that fits? We're always looking for talented people.</p>\n            <NuxtLink to=\"/contact\" class=\"btn-primary\">Send us your CV</NuxtLink>\n          </div>\n        </div>\n      </section>\n    </main>\n    <AppFooter />\n  </div>\n</template>\n\n<script setup lang=\"ts\">\nuseSeoMeta({\n  title: 'Careers | Altisry',\n  description: 'Join the team building the future of open banking. See open roles at Altisry.',\n})\n\nconst perks = [\n  { emoji: '🌍', title: 'Remote-first', description: 'Work from anywhere. We have team members across 12 countries.' },\n  { emoji: '🏥', title: 'Health coverage', description: 'Comprehensive health, dental, and vision insurance for you and your family.' },\n  { emoji: '📈', title: 'Equity', description: 'Every employee gets meaningful equity. We win together.' },\n  { emoji: '🎓', title: 'Learning budget', description: '€2,000/year learning budget for courses, conferences, and books.' },\n  { emoji: '🏖️', title: 'Unlimited PTO', description: 'We trust you to manage your time. Take the time you need.' },\n  { emoji: '🚀', title: 'High impact', description: 'Directly shape the product that powers hundreds of financial services globally.' },\n]\n\nconst openRoles = [\n  { title: 'Senior Backend Engineer', department: 'Engineering', location: 'Remote (Europe)', type: 'Full-time' },\n  { title: 'Product Manager – Payments', department: 'Product', location: 'London / Remote', type: 'Full-time' },\n  { title: 'Senior Frontend Engineer', department: 'Engineering', location: 'Remote (Europe)', type: 'Full-time' },\n  { title: 'Compliance Manager', department: 'Legal & Compliance', location: 'London', type: 'Full-time' },\n  { title: 'Sales Engineer', department: 'Sales', location: 'Remote', type: 'Full-time' },\n  { title: 'DevSecOps Engineer', department: 'Engineering', location: 'Remote (Europe)', type: 'Full-time' },\n]\n</script>\n"],"version":3}